{
  "collectionName": "components_hero_hero_videos",
  "info": {
    "displayName": "HeroVideo"
  },
  "options": {},
  "attributes": {
    "bgvideo": {
      "type": "media",
      "multiple": false,
      "required": true,
      "allowedTypes": [
        "files",
        "videos"
      ]
    },
    "title": {
      "type": "string"
    },
    "description": {
      "type": "string"
    },
    "notes": {
      "type": "string"
    },
    "buttonText": {
      "type": "string"
    },
    "buttonLink": {
      "type": "string"
    },
    "overlayPosition": {
      "type": "string"
    },
    "enabled": {
      "type": "boolean",
      "required": true,
      "default": false
    }
  },
  "config": {}
}
